Metadata-Version: 1.2
Name: btq2
Version: 0.0.2
Summary: please input trading path
Home-page: http://pdc.yfish.x/
Author: btq
Author-email: sakaiay_btq@163.com
License: UNKNOWN
Platform: UNKNOWN
Classifier: Programming Language :: Python :: 3
Classifier: License :: OSI Approved :: MIT License
Classifier: Operating System :: OS Independent
Requires-Python: >=3
